github_api_helper.py
requests_helper.py
muscle_musedev-0.0.6.1.data/scripts/muscle
muscle_musedev-0.0.6.1.dist-info/LICENSE
muscle_musedev-0.0.6.1.dist-info/METADATA
muscle_musedev-0.0.6.1.dist-info/WHEEL
muscle_musedev-0.0.6.1.dist-info/top_level.txt
muscle_musedev-0.0.6.1.dist-info/RECORD
