Metadata-Version: 2.1
Name: muscle-musedev
Version: 0.0.6.1
Summary: A CLI for running Muse jobs
Home-page: https://gitlab.com/musedev/muscle
Author: MuseDev
Author-email: support@emuse.dev
License: UNKNOWN
Platform: UNKNOWN
Classifier: Programming Language :: Python :: 3
Classifier: License :: OSI Approved :: MIT License
Classifier: Operating System :: OS Independent
Requires-Python: >=3.6
Requires-Dist: click
Requires-Dist: requests
